odoo/addons/purchase_order_approved/README.rst
odoo/addons/purchase_order_approved/__init__.py
odoo/addons/purchase_order_approved/__manifest__.py
odoo/addons/purchase_order_approved/i18n/am.po
odoo/addons/purchase_order_approved/i18n/ar.po
odoo/addons/purchase_order_approved/i18n/ca.po
odoo/addons/purchase_order_approved/i18n/da.po
odoo/addons/purchase_order_approved/i18n/de.po
odoo/addons/purchase_order_approved/i18n/el_GR.po
odoo/addons/purchase_order_approved/i18n/es.po
odoo/addons/purchase_order_approved/i18n/es_ES.po
odoo/addons/purchase_order_approved/i18n/es_MX.po
odoo/addons/purchase_order_approved/i18n/eu.po
odoo/addons/purchase_order_approved/i18n/fi.po
odoo/addons/purchase_order_approved/i18n/fr.po
odoo/addons/purchase_order_approved/i18n/fr_CA.po
odoo/addons/purchase_order_approved/i18n/fr_FR.po
odoo/addons/purchase_order_approved/i18n/gl.po
odoo/addons/purchase_order_approved/i18n/hr.po
odoo/addons/purchase_order_approved/i18n/hr_HR.po
odoo/addons/purchase_order_approved/i18n/it.po
odoo/addons/purchase_order_approved/i18n/nb.po
odoo/addons/purchase_order_approved/i18n/nb_NO.po
odoo/addons/purchase_order_approved/i18n/nl.po
odoo/addons/purchase_order_approved/i18n/nl_BE.po
odoo/addons/purchase_order_approved/i18n/nl_NL.po
odoo/addons/purchase_order_approved/i18n/pt_BR.po
odoo/addons/purchase_order_approved/i18n/purchase_order_approved.pot
odoo/addons/purchase_order_approved/i18n/ro.po
odoo/addons/purchase_order_approved/i18n/sk.po
odoo/addons/purchase_order_approved/i18n/sl.po
odoo/addons/purchase_order_approved/i18n/tr.po
odoo/addons/purchase_order_approved/i18n/vi_VN.po
odoo/addons/purchase_order_approved/i18n/zh_CN.po
odoo/addons/purchase_order_approved/models/__init__.py
odoo/addons/purchase_order_approved/models/purchase_order.py
odoo/addons/purchase_order_approved/models/res_company.py
odoo/addons/purchase_order_approved/models/res_config.py
odoo/addons/purchase_order_approved/readme/CONFIGURE.rst
odoo13_addon_purchase_order_approved-13.0.1.1.0.dist-info/METADATA
odoo13_addon_purchase_order_approved-13.0.1.1.0.dist-info/WHEEL
odoo13_addon_purchase_order_approved-13.0.1.1.0.dist-info/top_level.txt
odoo13_addon_purchase_order_approved-13.0.1.1.0.dist-info/RECORD
